secret_cli/__init__.py
secret_cli/main.py
secret_cli-0.0.12.dist-info/METADATA
secret_cli-0.0.12.dist-info/WHEEL
secret_cli-0.0.12.dist-info/entry_points.txt
secret_cli-0.0.12.dist-info/RECORD
